progressbarfwx/__init__.py
progressbarfwx/main.py
progressbar_fwx-1.5.dist-info/LICENCE
progressbar_fwx-1.5.dist-info/METADATA
progressbar_fwx-1.5.dist-info/WHEEL
progressbar_fwx-1.5.dist-info/top_level.txt
progressbar_fwx-1.5.dist-info/RECORD
