Metadata-Version: 2.1
Name: progressbar-fwx
Version: 1.5
Summary: Best And Most LightWeigt Progressbar Displayer!
Author-email: F1xGOD <f1xgodim@gmail.com>
Project-URL: Homepage, https://github.com/F1xGOD/progressbar-fwx
Project-URL: Issues, https://github.com/F1xGOD/progressbar-fwx/issues
Classifier: Programming Language :: Python :: 3
Classifier: License :: OSI Approved :: GNU General Public License v3 or later (GPLv3+)
Classifier: Operating System :: OS Independent
Requires-Python: >=3.8
License-File: LICENCE
